{
  "schema_version": 1,
  "id": "concorda-web::src/lib/api.ts::boatfinderApi.list",
  "kind": "service",
  "title": "boatfinderApi.list",
  "feature": null,
  "source": {
    "repo": "concorda-web",
    "path": "src/lib/api.ts",
    "symbol": "boatfinderApi.list",
    "line": 790
  },
  "signature": {
    "name": "boatfinderApi.list",
    "kind": "service"
  },
  "structural_hash": "7bda7dacd587cc8787d65d41cd82cbfd51cf94972173b64b4a75907d2eb7b3d3",
  "depends_on": [
    {
      "target": "GET::/api/boatfinder/search{0}",
      "via": "string_url",
      "where": "api.ts:796",
      "confidence": "fuzzy"
    }
  ],
  "external_consumers": [],
  "tests": [],
  "dossier": "dossiers/services/concorda_web__src_lib_api_ts__boatfinderApi_list.md",
  "extractor": "extract_web.ts",
  "warnings": []
}
