{
  "depends_on": [
    {
      "confidence": "exact",
      "target": "concorda-api::utils/websocket_manager.py::broadcast_event",
      "via": "websocket",
      "where": "routers/boats.py:455"
    },
    {
      "confidence": "exact",
      "target": "concorda-api::models/boat_crew.py::BoatCrew",
      "via": "db_query",
      "where": "routers/boats.py:449"
    },
    {
      "confidence": "exact",
      "target": "concorda-api::models/pending_crew_invite.py::PendingCrewInvite",
      "via": "db_query",
      "where": "routers/boats.py:458"
    }
  ],
  "dossier": "dossiers/endpoints/DELETE___api_boats_0_crew_1.md",
  "external_consumers": [],
  "extractor": "extract_api.py",
  "feature": null,
  "id": "DELETE::/api/boats/{0}/crew/{1}",
  "kind": "endpoint",
  "schema_version": 1,
  "signature": {
    "auth": "user",
    "method": "DELETE",
    "path": "/api/boats/{boat_id}/crew/{crew_id}",
    "request_schema_ref": null,
    "response_schema_ref": null
  },
  "source": {
    "line": 439,
    "path": "routers/boats.py",
    "repo": "concorda-api",
    "symbol": "remove_crew"
  },
  "structural_hash": "67b6dc6f4dbf77cd99bbacf01e271a0412912f1242baa433e6275597a2712816",
  "tests": [],
  "title": "DELETE /api/boats/{boat_id}/crew/{crew_id}",
  "warnings": []
}
